DisMail/__init__.py
DisMail/__main__.py
DisMail/api/__init__.py
DisMail/api/secmail/__init__.py
DisMail/api/secmail/account.py
DisMail/api/secmail/inbox.py
DisMail/api/secmail/classes/Inbox.py
DisMail/api/secmail/classes/Mail.py
DisMail/api/secmail/classes/__init__.py
DisMail/display/__init__.py
DisMail/mailutils/__init__.py
DisMail/mailutils/generators.py
DisMail-1.0.1.dist-info/LICENSE
DisMail-1.0.1.dist-info/METADATA
DisMail-1.0.1.dist-info/WHEEL
DisMail-1.0.1.dist-info/entry_points.txt
DisMail-1.0.1.dist-info/top_level.txt
DisMail-1.0.1.dist-info/RECORD
