Metadata-Version: 2.1
Name: DisMail
Version: 1.0.1
Summary: CLI to help you read your disposable emails straight from your console
Home-page: https://github.com/HanzCEO/DisMail
Author: Haxors
Author-email: hanzhaxors@gmail.com
License: UNLICENSED
Platform: UNKNOWN
Classifier: License :: OSI Approved :: The Unlicense (Unlicense)
Classifier: Programming Language :: Python :: 3
Classifier: Programming Language :: Python :: 3.7
License-File: LICENSE
Requires-Dist: requests (==2.26.0)
Requires-Dist: click (==8.0.3)
